{"SECOND":"second","CUSTOM_YEARLY_BYMONTH_INTERVAL_FORMAT":"Every %u years in %@","14th":"14th","26th":"26th","19th":"19th","FIRST":"first","2nd":"2nd","23rd":"23rd","9th":"9th","CUSTOM_MONTHLY_LASTDAY_INTERVAL_FORMAT":"Every %u months on the last day","CUSTOM_WEEKLY_WEEKENDS":"Weekends","6th":"6th","10th":"10th","15th":"15th","21st":"21st","CUSTOM_MONTHLY_BYMONTHDAY_INTERVAL_FORMAT":"Every %u months, each %@","CUSTOM_WEEKLY_WEEKDAYS":"Weekdays","27th":"27th","LAST_LIST_ITEM":", and %@","22nd":"22nd","CUSTOM_YEARLY_BYMONTH_FORMAT":"Every year in %@","CUSTOM_MONTHLY_SKIPPINGSHORTMONTHS_FORMAT":"Every month that has %u days","CUSTOM_MONTHLY_BYDAY_FORMAT":"Every month on the %@","CUSTOM_YEARLY_INTERVAL_FORMAT":"Every %u years","LAST":"last","11th":"11th","16th":"16th","30th":"30th","28th":"28th","8th":"8th","LAST_SECOND_LIST_ITEM":" and %@","5th":"5th","CUSTOM_DAILY_INTERVAL_FORMAT":"Every %u days","FOURTH":"fourth","3rd":"3rd","CUSTOM_MONTHLY_BYMONTHDAY_FORMAT":"Every month, each %@","CUSTOM_MONTHLY_BYDAY_INTERVAL_FORMAT":"Every %u months on the %@","12th":"12th","1st":"1st","CUSTOM_MONTHLY_SKIPPINGSHORTMONTHS_INTERVAL_FORMAT":"Every %u months that have %u days","24th":"24th","17th":"17th","29th":"29th","CUSTOM_MONTHLY_LASTDAY_FORMAT":"Every month on the last day","THIRD":"third","CUSTOM_MONTHLY_INTERVAL_FORMAT":"Every %u months","CUSTOM_YEARLY_BYDAY_INTERVAL_FORMAT":"Every %u years on the %@ of %@","13th":"13th","7th":"7th","20th":"20th","18th":"18th","25th":"25th","31st":"31st","CUSTOM_YEARLY_BYDAY_FORMAT":"Every year on the %@ of %@","CUSTOM_WEEKLY_INTERVAL_FORMAT":"Every %u weeks","4th":"4th","CUSTOM_BYDAY_ITEM_FORMAT":"%@ %@","CUSTOM_WEEKLY_DAYS_FORMAT":"Every week on %@","CUSTOM_WEEKLY_DAYS_INTERVAL_FORMAT":"Every %u weeks on %@"}