{"441":"Chongqing","330":"Mbabane","552":"Christiansted","442":"Urumqi","331":"Maseru","220":"Tahiti","553":"Efate","443":"Kashgar","332":"Andorra la Vella","221":"Paramaribo","554":"Mata-Utu","110":"Hamburg","444":"Praia","222":"Paris","555":"Aden","111":"Easter Island","112":"Hanoi","445":"Willemstad","334":"Rio Branco","223":"Perm","556":"Mamoudzou","190":"Munich","113":"Harare","446":"The Settlement","335":"Fernando de Noronha","224":"Perth","557":"Gothenburg","80":"Dallas","191":"Muscat","558":"Malmö","114":"Havana","447":"Roseau","81":"Daly City","336":"Pristina","225":"Petaluma","192":"Napa","82":"Damascus","559":"New Salem","115":"Healdsburg","448":"Guayaquil","337":"Thimphu","83":"Dar es Salaam","226":"Philadelphia","193":"Naples","116":"Helsinki","84":"Darwin","449":"El-Aaiun","338":"Berkeley Heights","227":"Phnom Penh","85":"Denver","194":"Nairobi","117":"Hobart","86":"Detroit","339":"Acton","228":"Phoenix","87":"Djibouti","195":"Naters","118":"Hong Kong","229":"Pittsburgh","88":"Doha","89":"Douala","196":"Ndjamena","119":"Honolulu","197":"New Delhi","198":"New Orleans","560":"Creston","199":"New York","561":"Quebec City","450":"Ceuta","340":"Thessaloniki","451":"Stanley","341":"Heraklion","230":"Pleasanton","452":"Chuuk","30":"Basse-Terre","31":"Beijing","342":"Tel Aviv","231":"Podgorica","120":"Houston","453":"Pohnpei","32":"Beirut","33":"Belgrade","343":"Frankfurt","232":"Ponta Delgada","121":"Indianapolis","34":"Belize City","454":"Kosrae","35":"Benicia","233":"Port Louis","122":"Irkutsk","455":"Libreville","36":"Berkeley","37":"Berlin","345":"Fort St. John","234":"Port-au-Prince","123":"Islamabad","456":"St. Georges","38":"Bern","346":"Yangon","39":"Bishkek","235":"Portland","124":"Istanbul","457":"Saint Peter Port","347":"Matamoros","236":"Prague","125":"Jakarta","458":"Gibraltar","348":"Ojinaga","237":"Pyongyang","126":"Jerusalem","459":"Chengdu","349":"Santa Isabel","238":"Quito","127":"Johannesburg","239":"Rabat","128":"Kabul","129":"Kaliningrad","90":"Dubai","91":"Dublin","92":"Dushanbe","93":"Edinburgh","460":"Dalian","94":"El Paso","95":"Florence","461":"Hefei","350":"Sarajevo","96":"Fremont","97":"Fort-de-France","240":"Rangoon","462":"Lhasa","351":"Salzburg","98":"Foster City","99":"Freetown","241":"Recife","130":"Kampala","463":"Nanjing","352":"Lyon","242":"Redwood City","131":"Kathmandu","464":"Qingdao","353":"Marseille","243":"Regina","132":"Khartoum","465":"Shenyang","354":"Tbilisi","244":"Reykjavik","133":"Kiev","466":"Danmarkshavn","355":"Saskatoon","245":"Riga","134":"Kingston","467":"Ittoqqortoormiit","356":"Tórshavn","246":"Rio de Janeiro","135":"Kinshasa","468":"Thule","357":"Waitangi","40":"Bissau","247":"Riyadh","136":"Knoxville","41":"Blacksburg","469":"Banjul","358":"Makassar","42":"Bogotá","248":"Rome","137":"Kolkata","359":"Jayapura","43":"Bologna","44":"Boston","249":"Saint-Denis","138":"Krasnoyarsk","45":"Bratislava","500":"Puerto Vallarta","46":"Brasília","139":"Kuala Lumpur","47":"Bridgetown","501":"Kuching","48":"Brisbane","49":"Brussels","502":"Kingston","503":"Nauru","470":"Pontianak","504":"Alofi","471":"Douglas","360":"Antwerp","505":"Chatham Island","472":"Diego Garcia","361":"Alexandria","506":"Taiohae","250":"Salt Lake City","473":"St. Helier","362":"Chiang Mai","507":"Rikitea","251":"Samara","140":"Kuwait","474":"Tarawa","363":"Hamilton","508":"Port Moresby","252":"San Diego","142":"La Paz","475":"Kanton Island","364":"Kraków","509":"Karachi","253":"San Antonio","143":"Lagos","476":"Kiritimati","365":"Tirana","254":"San Bruno","144":"Las Vegas","477":"Moroni","366":"Windhoek","255":"San Carlos","145":"Lima","478":"Basseterre","367":"Nicosia","256":"San Francisco","146":"Lisbon","479":"George Town","368":"Apia","257":"San Jose","147":"Little Rock","369":"Salvador","258":"San José","148":"Ljubljana","259":"San Juan","510":"Saint-Pierre","149":"London","511":"Adamstown","400":"Mariehamn","512":"Gaza","401":"Bujumbura","513":"Hebron","402":"Porto-Novo","50":"Bucharest","480":"Kyzylorda","514":"Funchal","51":"Budapest","403":"Bandar Seri Begawan","52":"Buenos Aires","370":"St. John's","481":"Aqtobe","515":"Vincennes","404":"Kralendijk","53":"Burlingame","54":"Cairo","371":"The Valley","516":"Koror","260":"San Leandro","405":"Belem","55":"Calgary","482":"Atyrau","372":"McMurdo Station","56":"Canary Islands","517":"Novokuznetsk","261":"San Salvador","406":"Fortaleza","483":"Oral","57":"Canberra","373":"Amundsen-Scott Station","262":"San Marino","58":"Canton","518":"Yuzhno-Sakhalinsk","407":"Araguaina","151":"Los Altos","484":"Castries","59":"Cape Town","374":"Rothera Station","263":"San Mateo","519":"Petropavlovsk-Kamchatsky","408":"Maceio","152":"Los Angeles","485":"Monaco","375":"Palmer Station","264":"San Pablo","409":"Campo Grande","153":"Los Gatos","486":"Majuro","376":"Mawson Station","265":"San Rafael","154":"Louisville","487":"Kwajalein Atoll","377":"Davis Station","266":"San Ramon","155":"Luanda","488":"Hovd","378":"Casey Station","267":"Santa Clara","156":"Lusaka","489":"Choibalsan","379":"Vostok Station","268":"Santa Cruz","157":"Luxembourg","269":"Sanaa","158":"Macau","520":"Monticello","159":"Madison","410":"Cuiaba","521":"Kigali","411":"Santarém","300":"Turin","522":"Honiara","412":"Porto Velho","301":"Ulaanbaatar","523":"Jamestown","490":"Saipan","413":"Boa Vista","302":"UTC","524":"Longyearbyen","491":"Plymouth","380":"Dumont-d'Urville Station","414":"Manaus","303":"Vaduz","525":"Juba","270":"Santiago","492":"Blantyre","415":"Eirunepe","304":"Vallejo","381":"Syowa Station","526":"São Tomé","271":"Santo Domingo","160":"Madrid","416":"Nassau","305":"Valletta","493":"Cancun","382":"Macquarie Island Station","527":"Lower Prince's Quarter","272":"São Paulo","161":"Malabo","528":"Cockburn Town","417":"Glace Bay","306":"Vancouver","494":"Mérida","383":"Cordoba","273":"Seattle","162":"Male","529":"Port-aux-Français","418":"Moncton","307":"Verona","495":"Monterrey","384":"Salta","274":"Seoul","163":"Managua","419":"Happy Valley-Goose Bay","60":"Caracas","308":"Victoria","496":"Mazatlán","385":"San Salvador de Jujuy","61":"Cardiff","275":"Shanghai","164":"Manama","309":"Vienna","497":"Chihuahua","62":"Catanzaro","386":"Tucaman","63":"Cayenne","276":"Shenzhen","165":"Marigot","498":"Hermosillo","387":"Catamarca","64":"Charlotte","277":"Singapore","65":"Charlotte Amalie","166":"Manila","499":"Tijuana","388":"La Rioja","66":"Chennai","278":"Sioux Falls","167":"Maputo","67":"Chicago","389":"San Juan","68":"Chisinau","279":"Skopje","168":"Mecca","69":"Chita","530":"Fale","169":"Melbourne","531":"Dili","420":"Blanc-Sablon","310":"Vilnius","532":"Winamac","421":"Nipigon","311":"Vladivostok","200":"Niamey","533":"Marengo","422":"Thunder Bay","312":"Volgograd","201":"Nouakchott","534":"Petersburg","423":"Iqaluit","390":"Mendoza","202":"Noumea","424":"Pangnirtung","535":"Vevay","313":"Walnut Creek","10":"Anadyr","391":"San Luis","280":"Sofia","203":"Novato","11":"Antananarivo","425":"Resolute","536":"Tell City","314":"Warsaw","12":"Anchorage","170":"Memphis","392":"Rio Gallegos","204":"Novosibirsk","537":"Knox","426":"Atikokan","13":"Ankara","281":"St. John's","315":"Washington, D.C.","14":"Ashgabat","171":"Menlo Park","282":"St. Louis","205":"Nukuʻalofa","538":"Menominee","15":"Asmera","427":"Rankin Inlet","393":"Ushuaia","316":"Wellington","172":"Messina","394":"Lord Howe Island","206":"Nuuk","539":"Center","16":"Astana","17":"Asunción","428":"Rainy River","283":"St. Petersburg","317":"Winnipeg","173":"Mexico City","395":"Currie","207":"Oakland","18":"Athens","284":"Sunnyvale","429":"Swift Current","19":"Atlanta","318":"Yakutsk","174":"Miami","396":"Broken Hill","208":"Oklahoma City","285":"Stockholm","319":"Yamoussoukro","175":"Milan","397":"Lindeman Island","209":"Omaha","286":"Suva","176":"Milbank","398":"Eucla","287":"Sydney","177":"Milwaukee","0":"Abidjan","399":"Oranjestad","1":"Abu Dhabi","288":"Taipei","2":"Accra","178":"Minneapolis","3":"Adak","289":"Tallinn","4":"Addis Ababa","540":"Beulah","5":"Adelaide","179":"Minsk","6":"Albuquerque","7":"Algiers","541":"Boise","8":"Amman","70":"Cleveland","9":"Amsterdam","430":"Edmonton","71":"Colombo","431":"Cambridge Bay","542":"Shiprock","320":"Yaoundé","72":"Columbus","73":"Conakry","210":"Omsk","543":"Juneau","321":"Yekaterinburg","432":"Yellowknife","74":"Copenhagen","211":"Osaka","75":"Cupertino","100":"Gaborone","433":"Inuvik","544":"Sitka","76":"Cork","322":"Yerevan","212":"Oslo","77":"Crotone","101":"Galápagos Islands","434":"Dawson Creek","545":"Yakutat","323":"Zagreb","78":"Dhaka","290":"Tashkent","213":"Ottawa","546":"Nome","79":"Dakar","102":"Geneva","435":"Whitehorse","324":"Zurich","180":"Magadan","291":"Tegucigalpa","214":"Ouagadougou","547":"Metlakatla","103":"Genoa","436":"Dawson City","325":"Decatur","181":"Mogadishu","292":"Tehran","215":"Pacifica","104":"Georgetown","437":"Bantam Village","548":"Samarkand","293":"Ho Chi Minh City","182":"Monrovia","216":"Pago Pago","105":"Grytviken","438":"Lubumbashi","549":"Vatican City","327":"Vientiane","183":"Montevideo","294":"Tientsin","217":"Palermo","106":"Guam","328":"Lomé","439":"Rarotonga","184":"Montpelier","295":"Tokyo","218":"Palo Alto","107":"Guatemala City","329":"Brazzaville","185":"Montreal","296":"Toronto","219":"Panama City","108":"Gustavia","20":"Auckland","21":"Austin","186":"Moscow","297":"Tréhet","109":"Halifax","22":"Baghdad","23":"Baku","187":"Monterey","298":"Tripoli","24":"Baltimore","188":"Mountain View","25":"Bamako","299":"Tunis","26":"Bangkok","550":"Kingstown","189":"Mumbai","27":"Bangui","28":"Barcelona","440":"Harbin","551":"Road Town","29":"Bari"}