{"Can't get a description of port %d":"Can’t get a description of port %d","precondition failed":"precondition failed","FTP command not recognized by host: %@":"FTP command not recognized by host: %@","unimplemented":"unimplemented","Object not available for specified URL: %@":"Object not available for specified URL: %@","%.0f MB":"%.0f MB","Could not connect to host %@":"Could not connect to host %@","%.1f KB (1.0)":"%.1f KB","%.1f MB (10.0)":"%.1f MB","User login or password not recognized.":"User login or password not recognized.","created":"created","method not allowed":"method not allowed","requested range not satisfiable":"requested range not satisfiable","service unavailable":"service unavailable","unauthorized":"unauthorized","see other":"see other","redirected":"redirected","%.1f GB (1.0)":"%.1f GB","informational":"informational","found":"found","server error":"server error","bad request":"bad request","requested URL too long":"requested URL too long","continue":"continue","partial content":"partial content","%.1f GB (10.0)":"%.1f GB","success":"success","no longer exists":"no longer exists","Lost connection to host %@":"Lost connection to host %@","Detected a redirection loop while attempting to load URL %@":"Detected a redirection loop while attempting to load URL %@","unsupported version":"unsupported version","not modified":"not modified","Service unavailable for host %@":"Service unavailable for host %@","%.0f bytes":"%.0f bytes","0 bytes":"0 bytes","Could not read from %@":"Could not read from %@","no content":"no content","accepted":"accepted","no error":"no error","forbidden":"forbidden","%.1f KB (10.0)":"%.1f KB","%.1f MB (1.0)":"%.1f MB","%@ of %@":"%@ of %@","expectation failed":"expectation failed","multiple choices":"multiple choices","internal server error":"internal server error","proxy authentication required":"proxy authentication required","temporarily redirected":"temporarily redirected","bad gateway":"bad gateway","1 byte":"1 byte","unsupported media type":"unsupported media type","Don't know how to load URL %@":"Don’t know how to load URL %@","Couldn't open data connection for URL path: %@":"Couldn’t open data connection for URL path: %@","client error":"client error","request timed out":"request timed out","Bad header received from server":"Bad header received from server","request too large":"request too large","conflict":"conflict","gateway timed out":"gateway timed out","moved permanently":"moved permanently","%.0f GB":"%.0f GB","switching protocols":"switching protocols","%.1f KB (0.1)":"%.1f KB","HTTP request failed for URL %@:%@":"HTTP request failed for URL %@:%@","Can't connect to host %@ using port %d":"Can’t connect to host %@ using port %d","length required":"length required","Received unknown HTTP server response %@: %@":"Received unknown HTTP server response %@: %@","non-authoritative information":"non-authoritative information","reset content":"reset content","%@ (%@)":"%@ (%@)","needs proxy":"needs proxy","not found":"not found","Can't determine IP address of host: %@":"Can’t determine IP address of host: %@","Web form password":"Web form password","unknown":"unknown","payment required":"payment required","%.0f KB":"%.0f KB","unacceptable":"unacceptable"}