{"com.apple.scrod.braille.driver.hims.braillesense.66817":"Scroll Right","com.apple.scrod.braille.driver.hims.braillesense.65536":"Router","com.apple.scrod.braille.driver.hims.braillesense.66049":"F3","com.apple.scrod.braille.driver.hims.braillesense.18":"HIMS Braille Sense 18","com.apple.scrod.braille.driver.hims.braillesense.65537":"F1","com.apple.scrod.braille.driver.hims.braillesense.66561":"Scroll Left","com.apple.scrod.braille.driver.hims.braillesense.65793":"F2","com.apple.scrod.braille.driver.hims.braillesense.65539":"Status Router","NSHumanReadableCopyright":"Copyright © 2010 Apple Inc. All Rights Reserved.","com.apple.scrod.braille.driver.hims.braillesense.66305":"F4","com.apple.scrod.braille.driver.hims.braillesense.32":"HIMS Braille Sense 32"}