{"Off":"Off","Auto":"Auto","PROXY_AUTHENTICATION":"Authentication","PROXY_PORT":"Port","VPN":"VPN","DELETE_VPN":"Delete VPN","PROXY_TYPE":"Type","DELETE_VPN_CONFIRMATION":"Delete","SEND_ALL_TRAFFIC":"Send All Traffic","PROXY_PASSWORD":"Password","ENCRYPTION_LEVEL":"Encryption Level","ACCOUNT_NAME":"Account","PROXY_URL":"URL","GROUP_NAME":"Group Name","ADD_VPN":"Add Configuration","SHARED_SECRET":"Secret","ON_DEMAND":"Connect On Demand","SERVER":"Server","DISPLAY_NAME":"Description","DELETE_VPN?":"Delete VPN?","REQUIRED":"Required","PASS_HINT":"Ask Every Time","PROXY_SERVER":"Server","PROXY_LABEL":"Proxy","CERTIFICATE_LIST":"Certificate","AUTO":"Auto","MAXIMUM":"Maximum","ADD_VPN_ABBREVIATED":"Add Configuration","ENCRYPTION_LEVEL_ABBREVIATED":"Encryption Level","PROXY_USERNAME":"Username","PASSWORD":"Password","EAP_RSA":"RSA SecurID","Manual":"Manual","CERTIFICATE_BASED":"Use Certificate","NONE":"None"}